hackmeapp.py
hackme/__init__.py
hackme/arp_spoofing.py
hackme/bpdu.py
hackme/flycheck_udp_flood.py
hackme/helpers.py
hackme/mac_flood.py
hackme/syn_flood.py
hackme/udp_flood.py
hackme-1.0.0.dist-info/LICENSE
hackme-1.0.0.dist-info/METADATA
hackme-1.0.0.dist-info/WHEEL
hackme-1.0.0.dist-info/entry_points.txt
hackme-1.0.0.dist-info/top_level.txt
hackme-1.0.0.dist-info/RECORD
